langflow/version/__init__.py
langflow/version/version.py
langflow_law-1.0.20.dist-info/entry_points.txt
langflow_law-1.0.20.dist-info/LICENSE
langflow_law-1.0.20.dist-info/METADATA
langflow_law-1.0.20.dist-info/WHEEL
langflow_law-1.0.20.dist-info/RECORD
